thingitwrapper/__init__.py
thingitwrapper/grouped_cache.py
thingitwrapper/aux.py
thingitwrapper/branch.py
thingitwrapper/cached.py
thingitwrapper/misc.py
thingitwrapper/tag.py
thingitwrapper/commit.py
thingitwrapper/stub_cache.py
thingitwrapper-0.1.dist-info/top_level.txt
thingitwrapper-0.1.dist-info/RECORD
thingitwrapper-0.1.dist-info/WHEEL
thingitwrapper-0.1.dist-info/METADATA
thingitwrapper-0.1.dist-info/DESCRIPTION.rst
thingitwrapper-0.1.dist-info/metadata.json
