Metadata-Version: 2.0
Name: thingitwrapper
Version: 0.1
Summary: Wrapper for git command line tool. For now functionality is limited to git commands needed for git-aflow project.
Home-page: https://github.com/einmalfel/git-aflow
Author: Vasily Makarov
Author-email: einmalfel@gmail.com
License: GNU LGPL 2.1
Keywords: git wrapper parser git-aflow
Platform: UNKNOWN
Classifier: Development Status :: 2 - Pre-Alpha
Classifier: Environment :: Console
Classifier: Operating System :: POSIX :: Linux
Classifier: Programming Language :: Python :: 3 :: Only
Classifier: Programming Language :: Python :: 3.2
Classifier: Topic :: Software Development :: Version Control
Classifier: License :: OSI Approved :: GNU Lesser General Public License v2 or later (LGPLv2+)
Provides: thingitwrapper
